gtfs_functions/__init__.py
gtfs_functions/aux_functions.py
gtfs_functions/gtfs_functions.py
gtfs_functions/gtfs_plots.py
gtfs_functions-2.5.dist-info/METADATA
gtfs_functions-2.5.dist-info/WHEEL
gtfs_functions-2.5.dist-info/licenses/LICENSE.txt
gtfs_functions-2.5.dist-info/RECORD
