Metadata-Version: 2.1
Name: gtfs-functions
Version: 2.5
Summary: Package to easily wrangle GTFS files geospatially.
Project-URL: Homepage, https://github.com/Bondify/gtfs_functions/tree/master
Project-URL: Bug Tracker, https://github.com/Bondify/gtfs_functions/issues
Author-email: Santiago Toso <santiagoa.toso@gmail.com>
License-File: LICENSE.txt
Classifier: License :: OSI Approved :: MIT License
Classifier: Operating System :: OS Independent
Classifier: Programming Language :: Python :: 3
Requires-Python: >=3.8
Requires-Dist: boto3
Requires-Dist: branca>=0.6.0
Requires-Dist: folium>=0.14.0
Requires-Dist: geopandas
Requires-Dist: h3
Requires-Dist: jenkspy>=0.3.2
Requires-Dist: numpy
Requires-Dist: pandas
Requires-Dist: pendulum>=3.0.0
Requires-Dist: plotly>=5.13.0
Requires-Dist: shapely
Requires-Dist: unicode>=2.9
Requires-Dist: utm>=0.7.0
